nlbone/__init__.py
nlbone/container.py
nlbone/types.py
nlbone/adapters/__init__.py
nlbone/adapters/snowflake.py
nlbone/adapters/auth/__init__.py
nlbone/adapters/auth/async_auth_service.py
nlbone/adapters/auth/async_token_provider.py
nlbone/adapters/auth/auth_service.py
nlbone/adapters/auth/keycloak.py
nlbone/adapters/auth/token_provider.py
nlbone/adapters/cache/__init__.py
nlbone/adapters/cache/async_redis.py
nlbone/adapters/cache/memory.py
nlbone/adapters/cache/pubsub_listener.py
nlbone/adapters/cache/redis.py
nlbone/adapters/db/__init__.py
nlbone/adapters/db/postgres/__init__.py
nlbone/adapters/db/postgres/audit.py
nlbone/adapters/db/postgres/base.py
nlbone/adapters/db/postgres/engine.py
nlbone/adapters/db/postgres/query_builder.py
nlbone/adapters/db/postgres/repository.py
nlbone/adapters/db/postgres/schema.py
nlbone/adapters/db/postgres/types.py
nlbone/adapters/db/postgres/uow.py
nlbone/adapters/db/redis/__init__.py
nlbone/adapters/db/redis/client.py
nlbone/adapters/http_clients/__init__.py
nlbone/adapters/http_clients/pricing/__init__.py
nlbone/adapters/http_clients/pricing/async_pricing_service.py
nlbone/adapters/http_clients/pricing/pricing_service.py
nlbone/adapters/http_clients/uploadchi/__init__.py
nlbone/adapters/http_clients/uploadchi/uploadchi.py
nlbone/adapters/http_clients/uploadchi/uploadchi_async.py
nlbone/adapters/i18n/__init__.py
nlbone/adapters/i18n/engine.py
nlbone/adapters/i18n/loaders.py
nlbone/adapters/i18n/locales/fa-IR.json
nlbone/adapters/messaging/__init__.py
nlbone/adapters/messaging/event_bus.py
nlbone/adapters/messaging/rabbitmq.py
nlbone/adapters/outbox/__init__.py
nlbone/adapters/outbox/outbox_consumer.py
nlbone/adapters/outbox/outbox_repo.py
nlbone/adapters/percolation/__init__.py
nlbone/adapters/percolation/connection.py
nlbone/adapters/repositories/__init__.py
nlbone/adapters/ticketing/__init__.py
nlbone/adapters/ticketing/client.py
nlbone/config/__init__.py
nlbone/config/logging.py
nlbone/config/settings.py
nlbone-0.11.3.dist-info/METADATA
nlbone-0.11.3.dist-info/WHEEL
nlbone-0.11.3.dist-info/entry_points.txt
nlbone-0.11.3.dist-info/licenses/LICENSE
nlbone-0.11.3.dist-info/RECORD
