Metadata-Version: 2.4
Name: nlbone
Version: 0.11.3
Summary: Backbone package for interfaces and infrastructure in Python projects
Author-email: Amir Hosein Kahkbazzadeh <a.khakbazzadeh@gmail.com>
License: MIT
License-File: LICENSE
Requires-Python: >=3.10
Requires-Dist: aio-pika>=9.5.7
Requires-Dist: anyio>=4.0
Requires-Dist: cachetools>=6.2.0
Requires-Dist: cryptography~=45.0.4
Requires-Dist: dependency-injector>=4.48.1
Requires-Dist: elasticsearch==8.14.0
Requires-Dist: fastapi>=0.116
Requires-Dist: httpx>=0.27
Requires-Dist: makefun>=1.16.0
Requires-Dist: psycopg>=3.2.9
Requires-Dist: pydantic-settings>=2.0
Requires-Dist: pydantic>=2.0
Requires-Dist: python-dateutil~=2.9.0.post0
Requires-Dist: python-keycloak==5.8.1
Requires-Dist: redis~=6.4.0
Requires-Dist: sqlalchemy>=2.0
Requires-Dist: starlette>=0.47
Requires-Dist: typer>=0.17.4
Requires-Dist: uvicorn==0.35
